oru/__init__.py
oru/meter.py
pseg/__init__.py
pseg/meter.py
pseg-0.1.1.dist-info/LICENSE
pseg-0.1.1.dist-info/METADATA
pseg-0.1.1.dist-info/WHEEL
pseg-0.1.1.dist-info/entry_points.txt
pseg-0.1.1.dist-info/top_level.txt
pseg-0.1.1.dist-info/RECORD
